RidgeSpace/__init__.py
RidgeSpace/main.py
RidgeSpace/utils.py
RidgeSpace/version.py
RidgeSpace-0.1.6.dist-info/LICENSE
RidgeSpace-0.1.6.dist-info/METADATA
RidgeSpace-0.1.6.dist-info/WHEEL
RidgeSpace-0.1.6.dist-info/entry_points.txt
RidgeSpace-0.1.6.dist-info/top_level.txt
RidgeSpace-0.1.6.dist-info/RECORD
