Metadata-Version: 2.1
Name: RidgeSpace
Version: 0.1.6
Summary: Unravelling three-dimensionally dynamics of spatial multi-modal data
Home-page: http://pypi.python.org/pypi/RidgeSpace/
Author: Ruiqiao He
Author-email: ruiqiaohe@gmail.com
License: GPL
Platform: UNKNOWN
Classifier: Development Status :: 3 - Alpha
Classifier: License :: OSI Approved :: GNU General Public License v3 (GPLv3)
Classifier: Programming Language :: Python :: 3
Classifier: Programming Language :: Python :: 3.7
Classifier: Programming Language :: Python :: 3.8
Classifier: Programming Language :: Python :: 3.9
Classifier: Programming Language :: Python :: 3.10
Classifier: Programming Language :: Python :: 3.11
Classifier: Topic :: Scientific/Engineering :: Bio-Informatics
Requires-Python: >=3.7.1
Requires-Dist: matplotlib (>=3.5.0)
Requires-Dist: numpy
Requires-Dist: pandas
Requires-Dist: scipy
